mirage/__init__.py
mirage/command.py
mirage/djargparse.py
mirage/djargparse2.py
mirage/exceptions.py
mirage/fileable.py
mirage/flow.py
mirage/flow_next.py
mirage/mgargparse.py
mirage/mirage.py
mirage/project.py
mirage/version.py
mirage/workflows.py
mirage/backup/__init__.py
mirage/backup/backup.py
mirage/checker/__init__.py
mirage/checker/system.py
mirage/checker/update_check.py
mirage/configure/__init__.py
mirage/configure/configure.py
mirage/configure/miragefile.py
mirage/confscript/__init__.py
mirage/confscript/configurator.py
mirage/confscript/flow.py
mirage/confscript/read.py
mirage/confscript/settings.py
mirage/console/__init__.py
mirage/console/django_console.py
mirage/core/__init__.py
mirage/core/types.py
mirage/db/__init__.py
mirage/db/db.py
mirage/db/merge.py
mirage/db/migrate.py
mirage/db/reset.py
mirage/destroy/__init__.py
mirage/destroy/app.py
mirage/destroy/destroy.py
mirage/ejector/__init__.py
mirage/ejector/flow.py
mirage/generate/__init__.py
mirage/generate/app.py
mirage/generate/help.py
mirage/generate/model.py
mirage/generate/model_template.py
mirage/generate/pymodule.py
mirage/generate/serializer.py
mirage/generate/url_template.py
mirage/generate/urlpy.py
mirage/git/__init__.py
mirage/git/git.py
mirage/help/__init__.py
mirage/help/description.py
mirage/help/description_long.py
mirage/help/usage_flow.py
mirage/heroku/__init__.py
mirage/heroku/configure.py
mirage/heroku/templates/__init__.py
mirage/heroku/templates/procfile.py
mirage/heroku/templates/runtime.py
mirage/manage/__init__.py
mirage/manage/executor.py
mirage/manual/__init__.py
mirage/manual/info.py
mirage/manual/version.py
mirage/miragefile/__init__.py
mirage/miragefile/conf.py
mirage/miragefile/source.py
mirage/miragefile/source2.py
mirage/miragefile/source_secret.py
mirage/miragefile/utils.py
mirage/miragefile/parser/__init__.py
mirage/miragefile/parser/parser.py
mirage/package/__init__.py
mirage/package/package.py
mirage/package/pip.py
mirage/package/pipenv.py
mirage_django_lts-0.2.6.dist-info/LICENSE
mirage_django_lts-0.2.6.dist-info/METADATA
mirage_django_lts-0.2.6.dist-info/WHEEL
mirage_django_lts-0.2.6.dist-info/entry_points.txt
mirage_django_lts-0.2.6.dist-info/top_level.txt
mirage_django_lts-0.2.6.dist-info/RECORD
